ind/__init__.py
ind/ind.py
market/__init__.py
market/dataEngine/__init__.py
market/dataEngine/mysqlFuns.py
market/ind/__init__.py
market/ind/ind.py
market/mysqlFuns/__init__.py
market/mysqlFuns/mysqlFuns.py
market/search/__init__.py
market/search/finance_keys_20201023.xlsx
market/search/start.py
market/search/table.py
market/stock/__init__.py
market/stock/stock.py
mysqlFuns/__init__.py
mysqlFuns/mysqlFuns.py
stock/__init__.py
stock/finance_keys_20201023.xlsx
stock/ind.py
stock/mysqlFuns.py
stock/stock.py
stock/table.py
Astock-0.1.3.dist-info/METADATA
Astock-0.1.3.dist-info/WHEEL
Astock-0.1.3.dist-info/top_level.txt
Astock-0.1.3.dist-info/RECORD
