Metadata-Version: 2.1
Name: Astock
Version: 0.1.3
Summary: stock data analyse
Author: Jopil
Author-email: jopil@163.com
Classifier: Programming Language :: Python
Requires-Dist: pandas (>=1.3.5)
Requires-Dist: numpy (>=1.21.5)
Requires-Dist: xlrd (>=2.0.1)
